MANIFEST.in
README.txt
setup.py
docs/HISTORY.txt
docs/INSTALL.txt
docs/LICENSE.GPL
docs/LICENSE.txt
ploomcake/__init__.py
ploomcake/__init__.pyc
ploomcake.core.egg-info/PKG-INFO
ploomcake.core.egg-info/SOURCES.txt
ploomcake.core.egg-info/dependency_links.txt
ploomcake.core.egg-info/entry_points.txt
ploomcake.core.egg-info/namespace_packages.txt
ploomcake.core.egg-info/not-zip-safe
ploomcake.core.egg-info/requires.txt
ploomcake.core.egg-info/top_level.txt
ploomcake/core/__init__.py
ploomcake/core/config.py
ploomcake/core/configure.zcml
ploomcake/core/install_util.py
ploomcake/core/profiles.zcml
ploomcake/core/setuphandlers.py
ploomcake/core/skins.zcml
ploomcake/core/testing.py
ploomcake/core/version.txt
ploomcake/core/browser/__init__.py
ploomcake/core/browser/configure.zcml
ploomcake/core/browser/interfaces.py
ploomcake/core/browser/portal_tabs_view.py
ploomcake/core/browser/viewlets.py
ploomcake/core/browser/templates/defaultviewdisclaimer_viewlet.pt
ploomcake/core/browser/templates/document_reverserelateditems.pt
ploomcake/core/browser/templates/languageselector.pt
ploomcake/core/locales/ploomcake.core.pot
ploomcake/core/locales/update.sh
ploomcake/core/locales/it/LC_MESSAGES/ploomcake.core.po
ploomcake/core/profiles/collaboration_portal/import_steps.xml
ploomcake/core/profiles/collaboration_portal/metadata.xml
ploomcake/core/profiles/collaboration_portal/ploomcake.core.collaboration_portal_various.txt
ploomcake/core/profiles/collaboration_portal/registry.xml
ploomcake/core/profiles/default/actions.xml
ploomcake/core/profiles/default/browserlayer.xml
ploomcake/core/profiles/default/cssregistry.xml
ploomcake/core/profiles/default/import_steps.xml
ploomcake/core/profiles/default/jsregistry.xml
ploomcake/core/profiles/default/mailhost.xml
ploomcake/core/profiles/default/metadata.xml
ploomcake/core/profiles/default/ploomcake.core.default_various.txt
ploomcake/core/profiles/default/portlets.xml
ploomcake/core/profiles/default/propertiestool.xml
ploomcake/core/profiles/default/registry.xml
ploomcake/core/profiles/default/rolemap.xml
ploomcake/core/profiles/default/skins.xml
ploomcake/core/profiles/default/tinymce.xml
ploomcake/core/profiles/intranet/import_steps.xml
ploomcake/core/profiles/intranet/metadata.xml
