Metadata-Version: 1.0
Name: ploomcake.core
Version: 1.5
Summary: Ploomcake policy product
Home-page: https://github.com/ploomcake/ploomcake.core
Author: Andrea D'Este
Author-email: andrea.deste@redomino.com
License: GPL
Platform: UNKNOWN
Classifier: Framework :: Plone
Classifier: Programming Language :: Python
